setup.py
buildtimetrend/__init__.py
buildtimetrend/buildjob.py
buildtimetrend/collection.py
buildtimetrend/keenio.py
buildtimetrend/service.py
buildtimetrend/settings.py
buildtimetrend/stages.py
buildtimetrend/tools.py
buildtimetrend/travis.py
buildtimetrend/trend.py
buildtimetrend.egg-info/PKG-INFO
buildtimetrend.egg-info/SOURCES.txt
buildtimetrend.egg-info/dependency_links.txt
buildtimetrend.egg-info/requires.txt
buildtimetrend.egg-info/top_level.txt