Metadata-Version: 1.1
Name: buildtimetrend
Version: 0.3
Summary: Visualise what's trending in your build process
Home-page: https://buildtimetrend.github.io/
Author: Dieter Adriaenssens
Author-email: ruleant@users.sourceforge.net
License: AGPLv3+
Keywords: trends,charts,build,ci,timing data
Platform: UNKNOWN
Classifier: Development Status :: 4 - Beta
Classifier: Programming Language :: Python
Classifier: Programming Language :: Python :: 2.7
Classifier: Intended Audience :: Developers
Classifier: Operating System :: OS Independent
Classifier: License :: OSI Approved :: GNU Affero General Public License v3 or later (AGPLv3+)
Classifier: Topic :: Software Development :: Libraries :: Python Modules
Classifier: Topic :: Software Development :: Build Tools
Classifier: Topic :: Software Development :: Quality Assurance
